{
  "checksums": [
    {
      "id": "github_release/github.com/crate-ci/typos/v1.37.1/typos-v1.37.1-aarch64-apple-darwin.tar.gz",
      "checksum": "D88975C9DA6C9A0CF413B79A546C4264F8803C0148E3D8B4DD300B5B27F21D79",
      "algorithm": "sha256"
    },
    {
      "id": "github_release/github.com/crate-ci/typos/v1.37.1/typos-v1.37.1-aarch64-unknown-linux-musl.tar.gz",
      "checksum": "83FDFDD1AD1D3B30CDBC3F601D994CC28C378585F14339DE4499F65EA734FEBC",
      "algorithm": "sha256"
    },
    {
      "id": "github_release/github.com/crate-ci/typos/v1.37.1/typos-v1.37.1-x86_64-apple-darwin.tar.gz",
      "checksum": "311D7E187F5E516B10154D38E2E117EAF309C333FBCD6371A9B4BB605E8B0502",
      "algorithm": "sha256"
    },
    {
      "id": "github_release/github.com/crate-ci/typos/v1.37.1/typos-v1.37.1-x86_64-pc-windows-msvc.zip",
      "checksum": "D9CABE4232A23DB8B48BD560F5045C111C0C3E789C1F8AC4C2FBF091463B053C",
      "algorithm": "sha256"
    },
    {
      "id": "github_release/github.com/crate-ci/typos/v1.37.1/typos-v1.37.1-x86_64-unknown-linux-musl.tar.gz",
      "checksum": "F07F4DD3243886990914F7D0C0E766E4DB61E811FC20046E65B98CF1A036639B",
      "algorithm": "sha256"
    },
    {
      "id": "github_release/github.com/suzuki-shunsuke/nllint/v0.1.2/nllint_darwin_amd64.tar.gz",
      "checksum": "EAD8931E0F048904E9D85E45E90F4E3BDF13B5D2EE5F2BCCC35782BC3EC4CD8F",
      "algorithm": "sha256"
    },
    {
      "id": "github_release/github.com/suzuki-shunsuke/nllint/v0.1.2/nllint_darwin_arm64.tar.gz",
      "checksum": "0DB73E6DC366FBB1EABAAE3D65C9C1E2F8B8DD09D9022D436D46120DBD5B96FA",
      "algorithm": "sha256"
    },
    {
      "id": "github_release/github.com/suzuki-shunsuke/nllint/v0.1.2/nllint_linux_amd64.tar.gz",
      "checksum": "F903F622DF9C89A694BEC4218AC2957D1E579627B662DF92E53FF725A9597E5D",
      "algorithm": "sha256"
    },
    {
      "id": "github_release/github.com/suzuki-shunsuke/nllint/v0.1.2/nllint_linux_arm64.tar.gz",
      "checksum": "FE2F89E5B03A1EBF6079071CA5E2836350735A6B1000C975AE27525C4C077488",
      "algorithm": "sha256"
    },
    {
      "id": "github_release/github.com/suzuki-shunsuke/nllint/v0.1.2/nllint_windows_amd64.zip",
      "checksum": "7AAADA136832D8E9D251515CB177D19B664EDB4072E63696BCEA42DD2B2D34E0",
      "algorithm": "sha256"
    },
    {
      "id": "github_release/github.com/suzuki-shunsuke/nllint/v0.1.2/nllint_windows_arm64.zip",
      "checksum": "C1C92F73778BECCB6422F004B1113B0AA7060C3757AF39EB8DF3E0573167D681",
      "algorithm": "sha256"
    },
    {
      "id": "github_release/github.com/suzuki-shunsuke/pinact/v3.4.2/pinact_darwin_amd64.tar.gz",
      "checksum": "5E2A94BC37BDAEF84F409B0B811F4E56EBFFFAE227624B86D58A172085AB73AA",
      "algorithm": "sha256"
    },
    {
      "id": "github_release/github.com/suzuki-shunsuke/pinact/v3.4.2/pinact_darwin_arm64.tar.gz",
      "checksum": "354811A84886C99422269B39DEEC399C8A42CE97FCF2E586C4F2F6B57E1E63EE",
      "algorithm": "sha256"
    },
    {
      "id": "github_release/github.com/suzuki-shunsuke/pinact/v3.4.2/pinact_linux_amd64.tar.gz",
      "checksum": "CF2F26FF37F195FADB7E5368CD618733107F7EA92C808CA4256521FC4BD6EA4F",
      "algorithm": "sha256"
    },
    {
      "id": "github_release/github.com/suzuki-shunsuke/pinact/v3.4.2/pinact_linux_arm64.tar.gz",
      "checksum": "CF109ED679276D60414366719EA721744F75F7E27F6F7B8394C66F3412F86A64",
      "algorithm": "sha256"
    },
    {
      "id": "github_release/github.com/suzuki-shunsuke/pinact/v3.4.2/pinact_windows_amd64.zip",
      "checksum": "34715E03474BD94E9A873450771A0E78B369F17DBA580E7134C19728BFBA5846",
      "algorithm": "sha256"
    },
    {
      "id": "github_release/github.com/suzuki-shunsuke/pinact/v3.4.2/pinact_windows_arm64.zip",
      "checksum": "9DFC4477E4BC0DEB16B53A597F5759C04DB3BD37B2424CEE8644890A1F5D4B5B",
      "algorithm": "sha256"
    },
    {
      "id": "registries/github_content/github.com/aquaproj/aqua-registry/v4.421.0/registry.yaml",
      "checksum": "28F12785429274ADCFA97906A10D80FFC44D0FAEF7CF1560119A31EA218C118E0C173C7FAEDDE31449665D25741B12F40EF3FFFCA4540947BE96D5CD370A92DE",
      "algorithm": "sha512"
    }
  ]
}
